bionic_falcon/__init__.py
bionic_falcon/asgi_resource.py
bionic_falcon/auth.py
bionic_falcon/db_session.py
bionic_falcon/middleware.py
bionic_falcon/resource.py
bionic_falcon/schema.py
bionic_falcon/test.py
bionic_falcon/test_after_methods.py
bionic_falcon/test_auth.py
bionic_falcon/test_base.py
bionic_falcon/test_before_methods.py
bionic_falcon/test_collection_patch.py
bionic_falcon/test_delete.py
bionic_falcon/test_fields.py
bionic_falcon/test_fixtures.py
bionic_falcon/test_join.py
bionic_falcon/test_meta.py
bionic_falcon/test_methods.py
bionic_falcon/test_middleware.py
bionic_falcon/test_modify_patch.py
bionic_falcon/test_preconditions.py
bionic_falcon/test_property.py
bionic_falcon/test_schema.py
bionic_falcon/test_serialize.py
bionic_falcon/test_sort.py
bionic_falcon/test_subresource.py
bionic_falcon/test_types.py
bionic_falcon-1.1.0.dist-info/LICENSE.txt
bionic_falcon-1.1.0.dist-info/METADATA
bionic_falcon-1.1.0.dist-info/WHEEL
bionic_falcon-1.1.0.dist-info/top_level.txt
bionic_falcon-1.1.0.dist-info/RECORD
