Metadata-Version: 2.1
Name: bionic-falcon
Version: 1.1.0
Summary: Automate CRUD actions with a Falcon API
Home-page: https://github.com/enodoscore/falcon-autocrud
Author: Gary Monson, Cami McCarthy
Author-email: camilla@enodoinc.com
License: MIT
Keywords: falcon crud rest database
Platform: UNKNOWN
Classifier: Development Status :: 4 - Beta
Classifier: Intended Audience :: Developers
Classifier: License :: OSI Approved :: MIT License
Classifier: Programming Language :: Python :: 3
Classifier: Programming Language :: Python :: 3.4
Classifier: Topic :: Database :: Front-Ends
Classifier: Topic :: Internet :: WWW/HTTP
Classifier: Topic :: Internet :: WWW/HTTP :: Dynamic Content
Classifier: Topic :: Internet :: WWW/HTTP :: WSGI :: Middleware
License-File: LICENSE.txt
Requires-Dist: falcon (>=2.0.0)
Requires-Dist: jsonschema
Requires-Dist: sqlalchemy
